LICENSE
README.md
setup.py
grammarly_scraper.egg-info/PKG-INFO
grammarly_scraper.egg-info/SOURCES.txt
grammarly_scraper.egg-info/dependency_links.txt
grammarly_scraper.egg-info/requires.txt
grammarly_scraper.egg-info/top_level.txt
pypi_scraper/__init__.py